socialscience/__init__.py
socialscience/bivariate.py
socialscience/crosstab.py
socialscience/multivariate.py
socialscience/univariate.py
socialscience-0.2.1.dist-info/DESCRIPTION.rst
socialscience-0.2.1.dist-info/METADATA
socialscience-0.2.1.dist-info/RECORD
socialscience-0.2.1.dist-info/WHEEL
socialscience-0.2.1.dist-info/metadata.json
socialscience-0.2.1.dist-info/top_level.txt
