Metadata-Version: 2.0
Name: socialscience
Version: 0.2.1
Summary: UNKNOWN
Home-page: https://github.com/scarsellifi/socialscience.git
Author: Marco Scarselli
Author-email: scarselli@gmail.com
License: MIT
Platform: UNKNOWN
Requires-Dist: matplotlib
Requires-Dist: numpy
Requires-Dist: pandas
Requires-Dist: seaborn
